setup.py
libmproxyex/__init__.py
libmproxyex/cmdline.py
libmproxyex/dumpex.py
libmproxyex/flowwriter.py
libmproxyex/main.py
mitmdumpex.egg-info/PKG-INFO
mitmdumpex.egg-info/SOURCES.txt
mitmdumpex.egg-info/dependency_links.txt
mitmdumpex.egg-info/entry_points.txt
mitmdumpex.egg-info/requires.txt
mitmdumpex.egg-info/top_level.txt