Metadata-Version: 1.0
Name: mitmdumpex
Version: 0.0.4
Summary: mitmdump with extended functionalities
Home-page: UNKNOWN
Author: isra17
Author-email: isra017@gmail.com
License: UNKNOWN
Platform: UNKNOWN
